{"metadata": {"dbt_schema_version": "https://schemas.getdbt.com/dbt/run-results/v4.json", "dbt_version": "1.0.0", "generated_at": "2022-07-14T19:15:36.501677Z", "invocation_id": "1062d332-947c-4222-a8bf-12473f76db9b", "env": {}}, "results": [{"status": "success", "timing": [{"name": "compile", "started_at": "2022-07-14T19:15:35.755959Z", "completed_at": "2022-07-14T19:15:35.779923Z"}, {"name": "execute", "started_at": "2022-07-14T19:15:35.781821Z", "completed_at": "2022-07-14T19:15:35.781872Z"}], "thread_id": "Thread-3", "execution_time": 0.030051231384277344, "adapter_response": {}, "message": null, "failures": null, "unique_id": "model.snapchat_ads_source.stg_snapchat_ads__ad_history_tmp"}, {"status": "success", "timing": [{"name": "compile", "started_at": "2022-07-14T19:15:35.755490Z", "completed_at": "2022-07-14T19:15:35.780276Z"}, {"name": "execute", "started_at": "2022-07-14T19:15:35.782251Z", "completed_at": "2022-07-14T19:15:35.782287Z"}], "thread_id": "Thread-1", "execution_time": 0.03198099136352539, "adapter_response": {}, "message": null, "failures": null, "unique_id": "model.develop.my_first_dbt_model"}, {"status": "success", "timing": [{"name": "compile", "started_at": "2022-07-14T19:15:35.755750Z", "completed_at": "2022-07-14T19:15:35.780497Z"}, {"name": "execute", "started_at": "2022-07-14T19:15:35.782668Z", "completed_at": "2022-07-14T19:15:35.782696Z"}], "thread_id": "Thread-2", "execution_time": 0.032103776931762695, "adapter_response": {}, "message": null, "failures": null, "unique_id": "model.snapchat_ads_source.stg_snapchat_ads__ad_account_history_tmp"}, {"status": "success", "timing": [{"name": "compile", "started_at": "2022-07-14T19:15:35.756158Z", "completed_at": "2022-07-14T19:15:35.780678Z"}, {"name": "execute", "started_at": "2022-07-14T19:15:35.783023Z", "completed_at": "2022-07-14T19:15:35.783041Z"}], "thread_id": "Thread-4", "execution_time": 0.03167891502380371, "adapter_response": {}, "message": null, "failures": null, "unique_id": "model.snapchat_ads_source.stg_snapchat_ads__ad_hourly_report_tmp"}, {"status": "success", "timing": [{"name": "compile", "started_at": "2022-07-14T19:15:35.790856Z", "completed_at": "2022-07-14T19:15:35.864028Z"}, {"name": "execute", "started_at": "2022-07-14T19:15:35.864506Z", "completed_at": "2022-07-14T19:15:35.864520Z"}], "thread_id": "Thread-3", "execution_time": 0.07684493064880371, "adapter_response": {}, "message": null, "failures": null, "unique_id": "model.snapchat_ads_source.stg_snapchat_ads__ad_squad_history_tmp"}, {"status": "success", "timing": [{"name": "compile", "started_at": "2022-07-14T19:15:35.791084Z", "completed_at": "2022-07-14T19:15:35.871509Z"}, {"name": "execute", "started_at": "2022-07-14T19:15:35.873370Z", "completed_at": "2022-07-14T19:15:35.873384Z"}], "thread_id": "Thread-1", "execution_time": 0.08517813682556152, "adapter_response": {}, "message": null, "failures": null, "unique_id": "model.snapchat_ads_source.stg_snapchat_ads__ad_squad_hourly_report_tmp"}, {"status": "success", "timing": [{"name": "compile", "started_at": "2022-07-14T19:15:35.791518Z", "completed_at": "2022-07-14T19:15:35.872047Z"}, {"name": "execute", "started_at": "2022-07-14T19:15:35.874031Z", "completed_at": "2022-07-14T19:15:35.874041Z"}], "thread_id": "Thread-4", "execution_time": 0.08575797080993652, "adapter_response": {}, "message": null, "failures": null, "unique_id": "model.snapchat_ads_source.stg_snapchat_ads__campaign_hourly_report_tmp"}, {"status": "success", "timing": [{"name": "compile", "started_at": "2022-07-14T19:15:35.791306Z", "completed_at": "2022-07-14T19:15:35.871794Z"}, {"name": "execute", "started_at": "2022-07-14T19:15:35.874494Z", "completed_at": "2022-07-14T19:15:35.874507Z"}], "thread_id": "Thread-2", "execution_time": 0.08695721626281738, "adapter_response": {}, "message": null, "failures": null, "unique_id": "model.snapchat_ads_source.stg_snapchat_ads__campaign_history_tmp"}, {"status": "success", "timing": [{"name": "compile", "started_at": "2022-07-14T19:15:35.866418Z", "completed_at": "2022-07-14T19:15:35.873110Z"}, {"name": "execute", "started_at": "2022-07-14T19:15:35.875629Z", "completed_at": "2022-07-14T19:15:35.875639Z"}], "thread_id": "Thread-3", "execution_time": 0.011507987976074219, "adapter_response": {}, "message": null, "failures": null, "unique_id": "model.snapchat_ads_source.stg_snapchat_ads__creative_history_tmp"}, {"status": "success", "timing": [{"name": "compile", "started_at": "2022-07-14T19:15:35.879578Z", "completed_at": "2022-07-14T19:15:35.895457Z"}, {"name": "execute", "started_at": "2022-07-14T19:15:35.907483Z", "completed_at": "2022-07-14T19:15:35.907500Z"}], "thread_id": "Thread-1", "execution_time": 0.031907081604003906, "adapter_response": {}, "message": null, "failures": null, "unique_id": "model.snapchat_ads_source.stg_snapchat_ads__creative_url_tag_history_tmp"}, {"status": "success", "timing": [{"name": "compile", "started_at": "2022-07-14T19:15:35.885762Z", "completed_at": "2022-07-14T19:15:35.907718Z"}, {"name": "execute", "started_at": "2022-07-14T19:15:35.910022Z", "completed_at": "2022-07-14T19:15:35.910033Z"}], "thread_id": "Thread-2", "execution_time": 0.03241229057312012, "adapter_response": {}, "message": null, "failures": null, "unique_id": "model.develop.my_second_dbt_model"}, {"status": "success", "timing": [{"name": "compile", "started_at": "2022-07-14T19:15:35.891704Z", "completed_at": "2022-07-14T19:15:35.908912Z"}, {"name": "execute", "started_at": "2022-07-14T19:15:35.911632Z", "completed_at": "2022-07-14T19:15:35.911644Z"}], "thread_id": "Thread-3", "execution_time": 0.03272104263305664, "adapter_response": {}, "message": null, "failures": null, "unique_id": "test.develop.not_null_my_first_dbt_model_id.5fb22c2710"}, {"status": "success", "timing": [{"name": "compile", "started_at": "2022-07-14T19:15:35.913068Z", "completed_at": "2022-07-14T19:15:35.923653Z"}, {"name": "execute", "started_at": "2022-07-14T19:15:35.930154Z", "completed_at": "2022-07-14T19:15:35.930170Z"}], "thread_id": "Thread-1", "execution_time": 0.01989293098449707, "adapter_response": {}, "message": null, "failures": null, "unique_id": "test.develop.unique_my_first_dbt_model_id.16e066b321"}, {"status": "success", "timing": [{"name": "compile", "started_at": "2022-07-14T19:15:35.885319Z", "completed_at": "2022-07-14T19:15:36.111188Z"}, {"name": "execute", "started_at": "2022-07-14T19:15:36.111584Z", "completed_at": "2022-07-14T19:15:36.111597Z"}], "thread_id": "Thread-4", "execution_time": 0.23376893997192383, "adapter_response": {}, "message": null, "failures": null, "unique_id": "model.snapchat_ads_source.stg_snapchat_ads__ad_history"}, {"status": "success", "timing": [{"name": "compile", "started_at": "2022-07-14T19:15:35.923316Z", "completed_at": "2022-07-14T19:15:36.130554Z"}, {"name": "execute", "started_at": "2022-07-14T19:15:36.130978Z", "completed_at": "2022-07-14T19:15:36.130992Z"}], "thread_id": "Thread-2", "execution_time": 0.2180640697479248, "adapter_response": {}, "message": null, "failures": null, "unique_id": "model.snapchat_ads_source.stg_snapchat_ads__ad_account_history"}, {"status": "success", "timing": [{"name": "compile", "started_at": "2022-07-14T19:15:35.929597Z", "completed_at": "2022-07-14T19:15:36.173273Z"}, {"name": "execute", "started_at": "2022-07-14T19:15:36.173751Z", "completed_at": "2022-07-14T19:15:36.173773Z"}], "thread_id": "Thread-3", "execution_time": 0.25162196159362793, "adapter_response": {}, "message": null, "failures": null, "unique_id": "model.snapchat_ads_source.stg_snapchat_ads__ad_hourly_report"}, {"status": "success", "timing": [{"name": "compile", "started_at": "2022-07-14T19:15:35.931636Z", "completed_at": "2022-07-14T19:15:36.174443Z"}, {"name": "execute", "started_at": "2022-07-14T19:15:36.175579Z", "completed_at": "2022-07-14T19:15:36.175590Z"}], "thread_id": "Thread-1", "execution_time": 0.24537110328674316, "adapter_response": {}, "message": null, "failures": null, "unique_id": "model.snapchat_ads_source.stg_snapchat_ads__ad_squad_history"}, {"status": "success", "timing": [{"name": "compile", "started_at": "2022-07-14T19:15:36.113201Z", "completed_at": "2022-07-14T19:15:36.279529Z"}, {"name": "execute", "started_at": "2022-07-14T19:15:36.279884Z", "completed_at": "2022-07-14T19:15:36.279897Z"}], "thread_id": "Thread-4", "execution_time": 0.16767120361328125, "adapter_response": {}, "message": null, "failures": null, "unique_id": "model.snapchat_ads_source.stg_snapchat_ads__ad_squad_hourly_report"}, {"status": "success", "timing": [{"name": "compile", "started_at": "2022-07-14T19:15:36.132516Z", "completed_at": "2022-07-14T19:15:36.375966Z"}, {"name": "execute", "started_at": "2022-07-14T19:15:36.376398Z", "completed_at": "2022-07-14T19:15:36.376412Z"}], "thread_id": "Thread-2", "execution_time": 0.24481201171875, "adapter_response": {}, "message": null, "failures": null, "unique_id": "model.snapchat_ads_source.stg_snapchat_ads__campaign_hourly_report"}, {"status": "success", "timing": [{"name": "compile", "started_at": "2022-07-14T19:15:36.378570Z", "completed_at": "2022-07-14T19:15:36.385395Z"}, {"name": "execute", "started_at": "2022-07-14T19:15:36.385805Z", "completed_at": "2022-07-14T19:15:36.385818Z"}], "thread_id": "Thread-2", "execution_time": 0.00875401496887207, "adapter_response": {}, "message": null, "failures": null, "unique_id": "test.develop.not_null_my_second_dbt_model_id.151b76d778"}, {"status": "success", "timing": [{"name": "compile", "started_at": "2022-07-14T19:15:36.387695Z", "completed_at": "2022-07-14T19:15:36.394672Z"}, {"name": "execute", "started_at": "2022-07-14T19:15:36.397043Z", "completed_at": "2022-07-14T19:15:36.397059Z"}], "thread_id": "Thread-2", "execution_time": 0.010862112045288086, "adapter_response": {}, "message": null, "failures": null, "unique_id": "test.develop.unique_my_second_dbt_model_id.57a0f8c493"}, {"status": "success", "timing": [{"name": "compile", "started_at": "2022-07-14T19:15:36.184316Z", "completed_at": "2022-07-14T19:15:36.398589Z"}, {"name": "execute", "started_at": "2022-07-14T19:15:36.414676Z", "completed_at": "2022-07-14T19:15:36.414693Z"}], "thread_id": "Thread-1", "execution_time": 0.23293781280517578, "adapter_response": {}, "message": null, "failures": null, "unique_id": "model.snapchat_ads_source.stg_snapchat_ads__creative_history"}, {"status": "success", "timing": [{"name": "compile", "started_at": "2022-07-14T19:15:36.398433Z", "completed_at": "2022-07-14T19:15:36.417968Z"}, {"name": "execute", "started_at": "2022-07-14T19:15:36.430430Z", "completed_at": "2022-07-14T19:15:36.430449Z"}], "thread_id": "Thread-2", "execution_time": 0.03541207313537598, "adapter_response": {}, "message": null, "failures": null, "unique_id": "test.snapchat_ads_source.dbt_utils_unique_combination_of_columns_stg_snapchat_ads__ad_history_ad_id___fivetran_synced.f84924f13b"}, {"status": "success", "timing": [{"name": "compile", "started_at": "2022-07-14T19:15:36.418158Z", "completed_at": "2022-07-14T19:15:36.434663Z"}, {"name": "execute", "started_at": "2022-07-14T19:15:36.441804Z", "completed_at": "2022-07-14T19:15:36.441817Z"}], "thread_id": "Thread-1", "execution_time": 0.026855945587158203, "adapter_response": {}, "message": null, "failures": null, "unique_id": "test.snapchat_ads_source.dbt_utils_unique_combination_of_columns_stg_snapchat_ads__ad_account_history_ad_account_id___fivetran_synced.cd4fd6b0be"}, {"status": "success", "timing": [{"name": "compile", "started_at": "2022-07-14T19:15:36.434896Z", "completed_at": "2022-07-14T19:15:36.444623Z"}, {"name": "execute", "started_at": "2022-07-14T19:15:36.452107Z", "completed_at": "2022-07-14T19:15:36.452122Z"}], "thread_id": "Thread-2", "execution_time": 0.019107818603515625, "adapter_response": {}, "message": null, "failures": null, "unique_id": "test.snapchat_ads_source.dbt_utils_unique_combination_of_columns_stg_snapchat_ads__ad_hourly_report_ad_id__date_hour.1a4ef6182a"}, {"status": "success", "timing": [{"name": "compile", "started_at": "2022-07-14T19:15:36.281268Z", "completed_at": "2022-07-14T19:15:36.445773Z"}, {"name": "execute", "started_at": "2022-07-14T19:15:36.453240Z", "completed_at": "2022-07-14T19:15:36.453251Z"}], "thread_id": "Thread-4", "execution_time": 0.17345714569091797, "adapter_response": {}, "message": null, "failures": null, "unique_id": "model.snapchat_ads_source.stg_snapchat_ads__creative_url_tag_history"}, {"status": "success", "timing": [{"name": "compile", "started_at": "2022-07-14T19:15:36.176774Z", "completed_at": "2022-07-14T19:15:36.453457Z"}, {"name": "execute", "started_at": "2022-07-14T19:15:36.455496Z", "completed_at": "2022-07-14T19:15:36.455506Z"}], "thread_id": "Thread-3", "execution_time": 0.2813689708709717, "adapter_response": {}, "message": null, "failures": null, "unique_id": "model.snapchat_ads_source.stg_snapchat_ads__campaign_history"}, {"status": "success", "timing": [{"name": "compile", "started_at": "2022-07-14T19:15:36.444895Z", "completed_at": "2022-07-14T19:15:36.453764Z"}, {"name": "execute", "started_at": "2022-07-14T19:15:36.455961Z", "completed_at": "2022-07-14T19:15:36.455970Z"}], "thread_id": "Thread-1", "execution_time": 0.01380300521850586, "adapter_response": {}, "message": null, "failures": null, "unique_id": "test.snapchat_ads_source.dbt_utils_unique_combination_of_columns_stg_snapchat_ads__ad_squad_history_ad_squad_id___fivetran_synced.200b225a27"}, {"status": "success", "timing": [{"name": "compile", "started_at": "2022-07-14T19:15:36.456808Z", "completed_at": "2022-07-14T19:15:36.472384Z"}, {"name": "execute", "started_at": "2022-07-14T19:15:36.480247Z", "completed_at": "2022-07-14T19:15:36.480264Z"}], "thread_id": "Thread-2", "execution_time": 0.033017873764038086, "adapter_response": {}, "message": null, "failures": null, "unique_id": "test.snapchat_ads_source.dbt_utils_unique_combination_of_columns_stg_snapchat_ads__ad_squad_hourly_report_ad_squad_id__date_hour.774a407e69"}, {"status": "success", "timing": [{"name": "compile", "started_at": "2022-07-14T19:15:36.463779Z", "completed_at": "2022-07-14T19:15:36.479361Z"}, {"name": "execute", "started_at": "2022-07-14T19:15:36.488023Z", "completed_at": "2022-07-14T19:15:36.488037Z"}], "thread_id": "Thread-4", "execution_time": 0.03290987014770508, "adapter_response": {}, "message": null, "failures": null, "unique_id": "test.snapchat_ads_source.dbt_utils_unique_combination_of_columns_stg_snapchat_ads__campaign_hourly_report_campaign_id__date_hour.64293afa9c"}, {"status": "success", "timing": [{"name": "compile", "started_at": "2022-07-14T19:15:36.472785Z", "completed_at": "2022-07-14T19:15:36.488324Z"}, {"name": "execute", "started_at": "2022-07-14T19:15:36.490231Z", "completed_at": "2022-07-14T19:15:36.490242Z"}], "thread_id": "Thread-3", "execution_time": 0.027022123336791992, "adapter_response": {}, "message": null, "failures": null, "unique_id": "test.snapchat_ads_source.dbt_utils_unique_combination_of_columns_stg_snapchat_ads__creative_history_creative_id___fivetran_synced.c6f6c78b99"}, {"status": "success", "timing": [{"name": "compile", "started_at": "2022-07-14T19:15:36.473334Z", "completed_at": "2022-07-14T19:15:36.489487Z"}, {"name": "execute", "started_at": "2022-07-14T19:15:36.491232Z", "completed_at": "2022-07-14T19:15:36.491242Z"}], "thread_id": "Thread-1", "execution_time": 0.027522802352905273, "adapter_response": {}, "message": null, "failures": null, "unique_id": "test.snapchat_ads_source.dbt_utils_unique_combination_of_columns_stg_snapchat_ads__creative_url_tag_history_creative_id__param_key__updated_at.cc3fa6acbe"}, {"status": "success", "timing": [{"name": "compile", "started_at": "2022-07-14T19:15:36.491434Z", "completed_at": "2022-07-14T19:15:36.498898Z"}, {"name": "execute", "started_at": "2022-07-14T19:15:36.499288Z", "completed_at": "2022-07-14T19:15:36.499300Z"}], "thread_id": "Thread-2", "execution_time": 0.009922027587890625, "adapter_response": {}, "message": null, "failures": null, "unique_id": "test.snapchat_ads_source.dbt_utils_unique_combination_of_columns_stg_snapchat_ads__campaign_history_campaign_id___fivetran_synced.31b9fb6777"}], "elapsed_time": 1.141787052154541, "args": {"write_json": true, "use_colors": true, "printer_width": 80, "version_check": true, "partial_parse": true, "static_parser": true, "profiles_dir": "/Users/renee.li/.dbt", "send_anonymous_usage_stats": true, "event_buffer_size": 100000, "compile": true, "which": "generate", "rpc_method": "docs.generate", "indirect_selection": "eager"}}